{"_via_settings":{"ui":{"annotation_editor_height":25,"annotation_editor_fontsize":0.8,"leftsidebar_width":18,"image_grid":{"img_height":80,"rshape_fill":"none","rshape_fill_opacity":0.3,"rshape_stroke":"yellow","rshape_stroke_width":2,"show_region_shape":true,"show_image_policy":"all"},"image":{"region_label":"__via_region_id__","region_color":"__via_default_region_color__","region_label_font":"10px Sans","on_image_annotation_editor_placement":"NEAR_REGION"}},"core":{"buffer_size":18,"filepath":{},"default_filepath":""},"project":{"name":"CPC664_PCB_Bottom"}},"_via_img_metadata":{"CPC664_PCB_Bottom.png1901333":{"filename":"CPC664_PCB_Bottom.png","size":1901333,"regions":[{"shape_attributes":{"name":"rect","x":1466,"y":364,"width":70,"height":35},"region_attributes":{"name":"IC101"}},{"shape_attributes":{"name":"rect","x":1308,"y":196,"width":125,"height":59},"region_attributes":{"name":"IC102"}},{"shape_attributes":{"name":"rect","x":1309,"y":309,"width":121,"height":59},"region_attributes":{"name":"IC103"}},{"shape_attributes":{"name":"rect","x":1364,"y":425,"width":70,"height":37},"region_attributes":{"name":"IC104"}},{"shape_attributes":{"name":"rect","x":1238,"y":426,"width":73,"height":37},"region_attributes":{"name":"IC105"}},{"shape_attributes":{"name":"rect","x":1142,"y":135,"width":91,"height":38},"region_attributes":{"name":"IC106"}},{"shape_attributes":{"name":"rect","x":1069,"y":196,"width":176,"height":59},"region_attributes":{"name":"IC107"}},{"shape_attributes":{"name":"rect","x":1072,"y":314,"width":174,"height":59},"region_attributes":{"name":"IC108"}},{"shape_attributes":{"name":"rect","x":1117,"y":425,"width":69,"height":36},"region_attributes":{"name":"IC109"}},{"shape_attributes":{"name":"rect","x":915,"y":458,"width":64,"height":36},"region_attributes":{"name":"IC110"}},{"shape_attributes":{"name":"rect","x":817,"y":458,"width":73,"height":38},"region_attributes":{"name":"IC113"}},{"shape_attributes":{"name":"rect","x":783,"y":325,"width":172,"height":56},"region_attributes":{"name":"IC111"}},{"shape_attributes":{"name":"rect","x":648,"y":442,"width":37,"height":71},"region_attributes":{"name":"IC120"}},{"shape_attributes":{"name":"rect","x":586,"y":443,"width":36,"height":68},"region_attributes":{"name":"IC119"}},{"shape_attributes":{"name":"rect","x":530,"y":444,"width":35,"height":66},"region_attributes":{"name":"IC118"}},{"shape_attributes":{"name":"rect","x":467,"y":442,"width":38,"height":69},"region_attributes":{"name":"IC117"}},{"shape_attributes":{"name":"rect","x":409,"y":440,"width":35,"height":72},"region_attributes":{"name":"IC121"}},{"shape_attributes":{"name":"rect","x":408,"y":331,"width":38,"height":70},"region_attributes":{"name":"IC122"}},{"shape_attributes":{"name":"rect","x":469,"y":333,"width":37,"height":68},"region_attributes":{"name":"IC123"}},{"shape_attributes":{"name":"rect","x":529,"y":331,"width":36,"height":70},"region_attributes":{"name":"IC124"}},{"shape_attributes":{"name":"rect","x":586,"y":329,"width":39,"height":89},"region_attributes":{"name":"IC115"}},{"shape_attributes":{"name":"rect","x":650,"y":330,"width":32,"height":88},"region_attributes":{"name":"IC114"}},{"shape_attributes":{"name":"rect","x":296,"y":343,"width":59,"height":170},"region_attributes":{"name":"IC116"}},{"shape_attributes":{"name":"rect","x":210,"y":467,"width":67,"height":37},"region_attributes":{"name":"IC125"}},{"shape_attributes":{"name":"rect","x":914,"y":148,"width":64,"height":35},"region_attributes":{"name":"IC112\n"}}],"file_attributes":{}}},"_via_attributes":{"region":{"name":{"type":"text","description":"","default_value":""}},"file":{}},"_via_data_format_version":"2.0.10","_via_image_id_list":["CPC664_PCB_Bottom.png1901333"]}